{"nMIpdPhv2K5UoYBWO3pwUg==":"mbr-121x68.jpg","SI6o2a/CFEFg24AyL2ENWg==":"img-1188-216x215.jpg","e95E1hKL8wFXlpP4HiEBNQ==":"peace%20sign-225x225.jpg","CnEkp8ul028jehqSCvt7Sw==":"hello%20beautiful-225x225.jpg","IpkPKHxSB4wuOwxeEJKBLw==":"cake%20pic-191x263.jpg","MbYD2KL+G4AmpMBYP8cyxA==":"cake%20picture-216x233.jpg","ZkHGdLXd+cpRyYqbzf9SrA==":"3%20cakes-275x183.jpg","NgXAGbvg2Q3ct8EgkCyNVA==":"wedding%20cake-268x188.jpg","bAFuTOBoHjQpSyeFmc4LNw==":"chocolate%20cake-201x251.jpg","WdfuPW5UfJ5/uRcrHToxZw==":"tall%20cake-201x251.jpg","BbwsleO4J8qC8ZcNTGTirw==":"img-1188-672x668.jpg","vFqLY5RcqKn5p+FEc3zeAw==":"sea%20cake-194x259.jpg","A4WTSf8gFLtoHy4C2nHbTw==":"img-1187-828x1104.jpg","B2ALuDB3Ek8dYHO4OF+UOw==":"img-1283-656x647.jpg","mpRrWIMtS8cUgzRZ8slMug==":"img-1286-816x787.jpg","JAz428qsXuMkCVP/4xAudw==":"img-1287-672x568.jpg","XwixHw+hGU0plUieffZSQA==":"img-1288-828x426.jpg","hI0VbRCHW8QawtCr21lgoA==":"img-1289-672x670.jpg","/vCOW66KlOBzejDA9TXarQ==":"img-1292-696x526.jpg","pEfvDAfPLh/Kpvmb2CjcAA==":"img-1293-696x510.jpg","KXmoPX+8LOnrFKeLvOXfbA==":"img-1294-696x351.jpg","hb/SGKfJZCZVfs8MJygoFw==":"img-1295-696x536.jpg","LUx324tiAsBoe/de9d5ZHQ==":"img-1297-672x666.jpg","IYOGpZoZt1N9dqpr65vzAA==":"mbr-429x251.png"}